{
  "required": true,
  "package": "fzzyhmstrs.emi_loot.mixins",
  "compatibilityLevel": "JAVA_21",
  "mixins": [
    "AlternativeLootConditionAccessor",
    "AndLootFunctionAccessor",
    "ApplyBonusLootFunctionAccessor",
    "BoundedIntUnaryOperatorAccessor",
    "CombinedEntryAccessor",
    "ConditionalLootFunctionAccessor",
    "CopyNameLootFunctionAccessor",
    "DataPackContentsMixin",
    "EnchantmentsPredicateAccessor",
    "ExplorationMapLootFunctionAccessor",
    "FilteredLootFunctionAccessor",
    "ItemEntryAccessor",
    "LeafEntryAccessor",
    "LimitCountLootFunctionAccessor",
    "LootPoolAccessor",
    "LootPoolEntryAccessor",
    "LootTableAccessor",
    "LootTableEntryAccessor",
    "ModifyContentsLootFunctionAccessor",
    "ReferenceLootFunctionAccessor",
    "ReloadableRegistriesMixin",
    "SetBookCoverLootFunctionAccessor",
    "SetCountLootFunctionAccessor",
    "SetDamageLootFunctionAccessor",
    "SetEnchantmentsLootFunctionAccessor",
    "SetFireworkExplosionLootFunctionAccessor",
    "SetFireworksLootFunctionAccessor",
    "SetInstrumentLootFunctionAccessor",
    "SetItemLootFunctionAccessor",
    "SetLootTableLootFunctionAccessor",
    "SetNameLootFunctionAccessor",
    "SetOminousBottleAmplifierLootFunctionAccessor",
    "SetPotionLootFunctionAccessor",
    "SetStewEffectLootFunctionAccessor",
    "TagEntryAccessor",
    "VariantPredicateAccessor"
  ],
  "injectors": {
    "defaultRequire": 1
  }
}